sqlmodel_plus/__init__.py
sqlmodel_plus/sqlmodel_plus.py
sqlmodel_plus-0.2.2.dist-info/LICENSE
sqlmodel_plus-0.2.2.dist-info/METADATA
sqlmodel_plus-0.2.2.dist-info/WHEEL
sqlmodel_plus-0.2.2.dist-info/RECORD
