Metadata-Version: 2.1
Name: sqlmodel-plus
Version: 0.2.2
Summary: Extend SQLModel functionalities.
Author: Soami Charan
Author-email: charansoami@gmail.com
Requires-Python: >=3.8,<4.0
Classifier: Programming Language :: Python :: 3
Classifier: Programming Language :: Python :: 3.8
Classifier: Programming Language :: Python :: 3.9
Classifier: Programming Language :: Python :: 3.10
Classifier: Programming Language :: Python :: 3.11
Classifier: Programming Language :: Python :: 3.12
Requires-Dist: sqlmodel (>=0.0.14,<0.0.15)
